{
    "_links": {
        "self": {
            "href": ""
        },
        "type": {
            "href": "http:\/\/default\/rest\/type\/path_alias\/path_alias"
        }
    },
    "uuid": [
        {
            "value": "06e2c76b-4275-42a9-810d-62cd5236c4e1"
        }
    ],
    "langcode": [
        {
            "value": "und"
        }
    ],
    "path": [
        {
            "value": "\/webform\/newsletter_subscription\/confirmation"
        }
    ],
    "alias": [
        {
            "value": "\/form\/newsletter-subscription\/confirmation"
        }
    ],
    "status": [
        {
            "value": true
        }
    ]
}