{
    "_links": {
        "self": {
            "href": ""
        },
        "type": {
            "href": "http:\/\/default\/rest\/type\/path_alias\/path_alias"
        }
    },
    "uuid": [
        {
            "value": "4b04d702-96fd-4980-bed8-52ce4838a9bf"
        }
    ],
    "langcode": [
        {
            "value": "en"
        }
    ],
    "path": [
        {
            "value": "\/webform\/contact\/submissions"
        }
    ],
    "alias": [
        {
            "value": "\/form\/contact\/submissions"
        }
    ],
    "status": [
        {
            "value": true
        }
    ]
}